README.md
setup.py
kbarcz_school.egg-info/PKG-INFO
kbarcz_school.egg-info/SOURCES.txt
kbarcz_school.egg-info/dependency_links.txt
kbarcz_school.egg-info/top_level.txt
pypi_school_kb/__init__.py
pypi_school_kb/classroom.py
pypi_school_kb/student.py