Metadata-Version: 2.1
Name: kbarcz-school
Version: 1.0.0
Summary: Biblioteka do wyświetlania klas
Home-page: UNKNOWN
License: UNKNOWN
Platform: UNKNOWN
